{"dependencies":[{"name":"../InnerSubscriber","loc":{"line":2,"column":32}},{"name":"./subscribeTo","loc":{"line":3,"column":28}},{"name":"../Observable","loc":{"line":4,"column":27}}],"generated":{"js":"\"use strict\";\n\nObject.defineProperty(exports, \"__esModule\", {\n  value: true\n});\nexports.subscribeToResult = subscribeToResult;\n\nvar _InnerSubscriber = require(\"../InnerSubscriber\");\n\nvar _subscribeTo = require(\"./subscribeTo\");\n\nvar _Observable = require(\"../Observable\");\n\nfunction subscribeToResult(outerSubscriber, result, outerValue, outerIndex, innerSubscriber) {\n  if (innerSubscriber === void 0) {\n    innerSubscriber = new _InnerSubscriber.InnerSubscriber(outerSubscriber, outerValue, outerIndex);\n  }\n  if (innerSubscriber.closed) {\n    return undefined;\n  }\n  if (result instanceof _Observable.Observable) {\n    return result.subscribe(innerSubscriber);\n  }\n  return (0, _subscribeTo.subscribeTo)(result)(innerSubscriber);\n}\n//# sourceMappingURL=subscribeToResult.js.map\n/** PURE_IMPORTS_START _InnerSubscriber,_subscribeTo,_Observable PURE_IMPORTS_END */"},"hash":"01eb0f7f45d48b019415ee44908e8421"}