{"dependencies":[{"name":"./AnimationFrameAction","loc":{"line":2,"column":37}},{"name":"./AnimationFrameScheduler","loc":{"line":3,"column":40}}],"generated":{"js":"\"use strict\";\n\nObject.defineProperty(exports, \"__esModule\", {\n  value: true\n});\nexports.animationFrame = exports.animationFrameScheduler = undefined;\n\nvar _AnimationFrameAction = require(\"./AnimationFrameAction\");\n\nvar _AnimationFrameScheduler = require(\"./AnimationFrameScheduler\");\n\n/** PURE_IMPORTS_START _AnimationFrameAction,_AnimationFrameScheduler PURE_IMPORTS_END */\nvar animationFrameScheduler = /*@__PURE__*/exports.animationFrameScheduler = new _AnimationFrameScheduler.AnimationFrameScheduler(_AnimationFrameAction.AnimationFrameAction);\nvar animationFrame = exports.animationFrame = animationFrameScheduler;\n//# sourceMappingURL=animationFrame.js.map"},"hash":"55912f42b4620200fcb6a3242a68e704"}